sopel_roulette/__init__.py
sopel_roulette/plugin.py
sopel_roulette-0.1.0.dist-info/licenses/COPYING
sopel_roulette-0.1.0.dist-info/METADATA
sopel_roulette-0.1.0.dist-info/WHEEL
sopel_roulette-0.1.0.dist-info/entry_points.txt
sopel_roulette-0.1.0.dist-info/top_level.txt
sopel_roulette-0.1.0.dist-info/RECORD
