Metadata-Version: 2.4
Name: sopel-roulette
Version: 0.1.0
Summary: Sopel plugin clone of a mIRC script to let users play Russian roulette
Author-email: dgw <dgw@technobabbl.es>
License-Expression: EFL-2.0
Project-URL: Homepage, https://github.com/dgw/sopel-roulette
Project-URL: Bug Tracker, https://github.com/dgw/sopel-roulette/issues
Keywords: sopel,plugin,bot,irc
Platform: Linux x86, x86-64
Classifier: Intended Audience :: Developers
Classifier: Intended Audience :: System Administrators
Classifier: Topic :: Communications :: Chat :: Internet Relay Chat
Requires-Python: <4,>=3.8
License-File: COPYING
Requires-Dist: sopel>=8.0
Dynamic: license-file
